emek
