Metadata-Version: 2.1
Name: emek
Version: 1.0.1
Summary: Making Tag Analysis from Stack Overflow Questions Dataframe
Author-email: bakircius <burakbakirci@gmail.com>
License:                     GNU GENERAL PUBLIC LICENSE
Project-URL: Source, https://github.com/bakircius/emek
Project-URL: Issues, https://github.com/bakircius/emek/issues
Project-URL: Repository, https://github.com/bakircius/emek.git
Classifier: Programming Language :: Python :: 3
Classifier: License :: OSI Approved :: MIT License
Classifier: Operating System :: OS Independent
Requires-Python: >=3.8
License-File: LICENSE
Requires-Dist: requests
Requires-Dist: pandas
Requires-Dist: numpy
Requires-Dist: sosq
